driptorch/__init__.py
driptorch/_distance.py
driptorch/_grid.py
driptorch/_version.py
driptorch/errors.py
driptorch/io.py
driptorch/mapping.py
driptorch/pattern.py
driptorch/personnel.py
driptorch/templates.py
driptorch/unit.py
driptorch/warnings.py
driptorch/firing/__init__.py
driptorch/firing/_base.py
driptorch/firing/back.py
driptorch/firing/flank.py
driptorch/firing/head.py
driptorch/firing/inferno.py
driptorch/firing/ring.py
driptorch/firing/strip.py
driptorch/firing/strip_contour.py
driptorch-0.8.3.dist-info/LICENSE
driptorch-0.8.3.dist-info/METADATA
driptorch-0.8.3.dist-info/WHEEL
driptorch-0.8.3.dist-info/top_level.txt
driptorch-0.8.3.dist-info/RECORD
