Metadata-Version: 2.1
Name: driptorch
Version: 0.8.3
Summary: Ignition pattern simulator for prescribed firing techniques
Home-page: https://github.com/silvxlabs/DripTorch
Author: Silvx Labs
Author-email: lucas@silvxlabs.com
License: MIT
Keywords: ignition pattern,fire,firing techniques,prescribed burn
Classifier: Development Status :: 3 - Alpha
Classifier: Intended Audience :: Developers
Classifier: License :: OSI Approved :: MIT License
Classifier: Programming Language :: Python :: 3.10
Classifier: Programming Language :: Python :: 3.11
Classifier: Programming Language :: Python :: 3.12
License-File: LICENSE
Requires-Dist: Shapely
Requires-Dist: awkward
Requires-Dist: numpy
Requires-Dist: pandas
Requires-Dist: pyproj
Requires-Dist: folium
Requires-Dist: gcsfs
Requires-Dist: zarr
Requires-Dist: scipy
Requires-Dist: scikit-image
